infery.pyi
tests.cpython-37m-x86_64-linux-gnu.so
infery.cpython-38-x86_64-linux-gnu.so
infery.cpython-39-x86_64-linux-gnu.so
tests.cpython-39-x86_64-linux-gnu.so
tests.cpython-38-x86_64-linux-gnu.so
tests.pyi
infery.cpython-37m-x86_64-linux-gnu.so
infery_openvino-3.6.0.dist-info/METADATA
infery_openvino-3.6.0.dist-info/top_level.txt
infery_openvino-3.6.0.dist-info/WHEEL
infery_openvino-3.6.0.dist-info/LICENSE
infery_openvino-3.6.0.dist-info/RECORD
